{
    "version": "0.2",
    "$schema": "https://raw.githubusercontent.com/streetsidesoftware/cspell/main/cspell.schema.json",
    "enableGlobDot": true,
    "language": "en,es-ES,en-GB",
    "words": [
        "ADDSLOTS",
        "BITCOUNT",
        "BITFIELD",
        "BITOP",
        "BITPOS",
        "brenchmark",
        "BYLEX",
        "BYSCORE",
        "clientid",
        "decrby",
        "EXAT",
        "GETBIT",
        "getname",
        "Getname",
        "GETNAME",
        "getrange",
        "Getredir",
        "getset",
        "hdel",
        "HDEL",
        "hexists",
        "HEXISTS",
        "hgetall",
        "hincrby",
        "HINCRBY",
        "hincrbyfloat",
        "HINCRBYFLOAT",
        "hkeys",
        "HKEYS",
        "hlen",
        "HLEN",
        "hmget",
        "HMGET",
        "hset",
        "hsetnx",
        "HSETNX",
        "hstrlen",
        "HSTRLEN",
        "hvals",
        "HVALS",
        "incrby",
        "KEEPTTL",
        "lindex",
        "linsert",
        "llen",
        "LLEN",
        "lpop",
        "LPOP",
        "lpush",
        "LPUSH",
        "lrange",
        "lrem",
        "ltrim",
        "LTRIM",
        "MADD",
        "MEXISTS",
        "mget",
        "mockito",
        "mset",
        "MSET",
        "myset",
        "Nagle",
        "Numpat",
        "Numsub",
        "pmessage",
        "psubscribe",
        "punsubscribe",
        "PXAT",
        "redis",
        "renamenx",
        "rpop",
        "RPOP",
        "rpoplpush",
        "rpush",
        "sadd",
        "SADD",
        "scard",
        "sdiff",
        "sdiffstore",
        "SETBIT",
        "Setinfo",
        "Setname",
        "setrange",
        "Shardchannels",
        "SHARDCHANNELS",
        "Shardnumsub",
        "SHARDNUMSUB",
        "sinterstore",
        "sismember",
        "smembers",
        "smessage",
        "smove",
        "spop",
        "spublish",
        "Spublish",
        "srandmember",
        "srem",
        "ssubscribe",
        "strlen",
        "sunion",
        "sunionstore",
        "sunsubscribe",
        "TRACKINGINFO",
        "valkey",
        "Valkey",
        "WITHSCORES",
        "zadd",
        "zcard",
        "zcount",
        "zincrby",
        "zrange",
        "zrangebyscore",
        "zrank",
        "zrem",
        "zrevrange",
        "zrevrangebyscore",
        "zrevrank",
        "zscore",
        "zset"
    ],
    "useGitignore": true,
    "ignorePaths": [
        ".git/*",
        ".git/!{COMMIT_EDITMSG,EDITMSG}",
        ".git/*/**",
        ".vscode",
        ".gitignore",
        "cspell.json"
    ]
}
